{
    "breakfast": [
        "11월 29일 (수)",
        "쌀밥 & 굴소스볶음밥 10.15",
        "팽이우동장국",
        "계란후라이 1",
        "제육볶음 10",
        "가지나물"
    ],
    "simple_breakfast": [
        "배추김치",
        "야채샐러드",
        "시리얼&우유 2.6"
    ],
    "rich_lunch": [
        "토스트&잼 6",
        "순대고기국밥 10"
    ],
    "lunch": [
        "후렌치토스트 1.6",
        "흑미밥",
        "팽이우동장국",
        "함박구이 & 로제S 10.15",
        "단호박튀김",
        "맛살브로콜리볶음",
        "검정콩자반 5"
    ],
    "dinner": [
        "배추김치",
        "흑미밥",
        "대파사골국 & 소면 16",
        "맛쵸킹탕수육 10.15",
        "후랑크케찹볶음 10.15",
        "마늘쫑지무침",
        "피크닉"
    ]
}