{
    "breakfast": [
        "쌀밥 & 굴소스볶음밥 10.15",
        "얼갈이된장국",
        "계란후라이 1",
        "고기산적 10.15",
        "돌나물 & 초장",
        "배추김치"
    ],
    "simple_breakfast": [
        "야채샐러드",
        "시리얼&우유 2.6",
        "토스트&잼 6"
    ],
    "rich_lunch": [
        "야채튀김우동 9",
        "손만두찜 10"
    ],
    "lunch": [
        "흑미밥",
        "얼갈이된장국",
        "불닭돈육볶음 10",
        "연두부 & 양념장 5",
        "콩나물무침",
        "양념깻잎지",
        "배추김치"
    ],
    "dinner": [
        "흑미밥",
        "얼큰콩나물국",
        "맥앤치즈함박 10.15",
        "비엔나떡볶이 10.15",
        "열무된장나물",
        "검정콩자반 5",
        "배추김치"
    ]
}