{
    "breakfast": [
        "쌀밥 & 짜장볶음밥 10.15",
        "콩나물북어국",
        "계란후라이 1",
        "너비아니구이 10.15",
        "부추무생채",
        "배추김치"
    ],
    "simple_breakfast": [
        "야채샐러드",
        "시리얼&우유 2.6",
        "토스트&잼 6"
    ],
    "rich_lunch": [
        "뚝배기파스타 10.12.18",
        "계란샌드위치 1.6"
    ],
    "lunch": [
        "흑미밥",
        "콩나물북어국",
        "제육고추장볶음 10",
        "상추쌈 & 쌈장",
        "견과류멸치볶음",
        "고추장아찌",
        "배추김치"
    ],
    "dinner": [
        "불고기할라피뇨볶음밥 10",
        "옥수수스프",
        "돈가스 & 소스 10",
        "쫄면야채무침",
        "단무지부추무침",
        "식빵크루통 6",
        "배추김치"
    ]
}